textflow/__init__.py
textflow/auth.py
textflow/client.py
textflow/config.py
textflow/script.py
textflow/metrics/__init__.py
textflow/metrics/agreement.py
textflow/model/__init__.py
textflow/model/annotation.py
textflow/model/dataset.py
textflow/model/document.py
textflow/model/estimator.py
textflow/model/label.py
textflow/model/project.py
textflow/model/user.py
textflow/services/__init__.py
textflow/services/base.py
textflow/static/favicon.svg
textflow/static/fonts/Roboto/LICENSE.txt
textflow/static/fonts/Roboto/Roboto-Black.ttf
textflow/static/fonts/Roboto/Roboto-BlackItalic.ttf
textflow/static/fonts/Roboto/Roboto-Bold.ttf
textflow/static/fonts/Roboto/Roboto-BoldItalic.ttf
textflow/static/fonts/Roboto/Roboto-Italic.ttf
textflow/static/fonts/Roboto/Roboto-Light.ttf
textflow/static/fonts/Roboto/Roboto-LightItalic.ttf
textflow/static/fonts/Roboto/Roboto-Medium.ttf
textflow/static/fonts/Roboto/Roboto-MediumItalic.ttf
textflow/static/fonts/Roboto/Roboto-Regular.ttf
textflow/static/fonts/Roboto/Roboto-Thin.ttf
textflow/static/fonts/Roboto/Roboto-ThinItalic.ttf
textflow/static/images/classification.jpeg
textflow/static/images/custom_type.jpeg
textflow/static/images/logo.png
textflow/static/images/long-logo.png
textflow/static/images/sequence_classification.jpeg
textflow/static/scripts/annotator.js
textflow/static/scripts/base.js
textflow/static/scripts/fontawesome.all.js
textflow/static/scripts/handlebars.js
textflow/static/scripts/jquery-3.5.1.min.js
textflow/static/scripts/notify.min.js
textflow/static/scripts/theme.js
textflow/static/scripts/toastr.min.js
textflow/static/scripts/vue.js
textflow/static/scripts/vue.min.js
textflow/static/styles/annotator.css
textflow/static/styles/base.css
textflow/static/styles/bulma.css
textflow/static/styles/bulma.css.map
textflow/static/styles/bulma.min.css
textflow/static/styles/dash.css
textflow/static/styles/theme.css
textflow/static/styles/toastr.css
textflow/static/styles/toastr.min.css
textflow/templates/about.html
textflow-0.4.6.dist-info/LICENSE
textflow-0.4.6.dist-info/METADATA
textflow-0.4.6.dist-info/WHEEL
textflow-0.4.6.dist-info/entry_points.txt
textflow-0.4.6.dist-info/top_level.txt
textflow-0.4.6.dist-info/RECORD
