Metadata-Version: 2.1
Name: textflow
Version: 0.4.6
Summary: Simple and extensible framework for end to end text based natural language understanding.
Home-page: https://github.com/ysenarath/textflow
Author: Yasas Senarath
Author-email: ysenarath.93@gmail.com
Classifier: Programming Language :: Python :: 3
Classifier: License :: OSI Approved :: MIT License
Classifier: Operating System :: OS Independent
Requires-Python: >=3.6
License-File: LICENSE
Requires-Dist: Flask
Requires-Dist: WTForms
Requires-Dist: joblib
Requires-Dist: Werkzeug
Requires-Dist: scikit-learn (>=1.0.0)
Requires-Dist: pandas
Requires-Dist: nltk
Requires-Dist: SQLAlchemy
Requires-Dist: tqdm
Requires-Dist: requests
Requires-Dist: beautifulsoup4
Requires-Dist: click
Requires-Dist: numpy
Requires-Dist: packaging
Requires-Dist: Flask-Login
Requires-Dist: Flask-SQLAlchemy
Requires-Dist: sklearn-crfsuite
Requires-Dist: Flask-WTF
